terminal_gpt/__init__.py
terminal_gpt/suggest.py
fixcmd-0.1.4.dist-info/METADATA
fixcmd-0.1.4.dist-info/WHEEL
fixcmd-0.1.4.dist-info/entry_points.txt
fixcmd-0.1.4.dist-info/top_level.txt
fixcmd-0.1.4.dist-info/RECORD
