Metadata-Version: 2.4
Name: fixcmd
Version: 0.1.4
Summary: GPT-powered terminal assistant
Home-page: https://github.com/ragupari/terminal-gpt
Author: Parishith Ragumar
Author-email: ragupari07@gmail.com
Classifier: Programming Language :: Python :: 3
Classifier: Operating System :: OS Independent
Classifier: License :: OSI Approved :: MIT License
Requires-Python: >=3.7
Requires-Dist: openai>=1.0.0
Requires-Dist: python-dotenv
Dynamic: author
Dynamic: author-email
Dynamic: classifier
Dynamic: description
Dynamic: description-content-type
Dynamic: home-page
Dynamic: requires-dist
Dynamic: requires-python
Dynamic: summary
